attribs/__init__.py
attribs/attributes.py
attribs/base.py
attribs/create.py
attribs/py.typed
maya_attribs-0.1.0.dist-info/LICENSE
maya_attribs-0.1.0.dist-info/METADATA
maya_attribs-0.1.0.dist-info/WHEEL
maya_attribs-0.1.0.dist-info/top_level.txt
maya_attribs-0.1.0.dist-info/RECORD
