Metadata-Version: 2.1
Name: maya-attribs
Version: 0.1.0
Summary: A Python library for creating Maya Attributes
Author: Thibaud Gambier
License: MIT License
Keywords: maya,openmaya
Classifier: Development Status :: 4 - Beta
Classifier: License :: OSI Approved :: MIT License
Classifier: Programming Language :: Python :: 3.7
Classifier: Programming Language :: Python :: 3.8
Classifier: Programming Language :: Python :: 3.9
Classifier: Programming Language :: Python :: 3.10
Classifier: Programming Language :: Python :: 3.11
Classifier: Programming Language :: Python :: 3.12
Classifier: Programming Language :: Python :: Implementation :: CPython
Requires-Python: >=3.7
License-File: LICENSE
Requires-Dist: typing-extensions; python_version < "3.11"
